[
  { "word": "อาคาร", "count": 671, "summation": 69045505120 },
  { "word": "หลวง", "count": 471, "summation": 95333320679 },
  { "word": "ค่าเช่ารถ", "count": 357, "summation": 1816682133.33 },
  { "word": "ชาติ", "count": 603, "summation": 21166969024 },
  { "word": "พระราชดำริ", "count": 23, "summation": 6239328400 },
  { "word": "จ้างที่ปรึกษา", "count": 44, "summation": 626949600 },
  { "word": "เฉลิมพระเกียรติ", "count": 21, "summation": 6649817420 },
  { "word": "ขุดลอก", "count": 2, "summation": 176647400 },
  { "word": "ค่าที่ดิน", "count": 2433, "summation": 231758862723 },
  { "word": "เสด็จ", "count": 12, "summation": 387557100 },
  { "word": "ถวาย", "count": 12, "summation": 481518400 },
  { "word": "ศาสน", "count": 9, "summation": 31012300 },
  { "word": "กษัตริย์", "count": 9, "summation": 170907200 },
  { "word": "คุณธรรม", "count": 3, "summation": 9693200 },
  { "word": "Big Data", "count": 1, "summation": 2152100 },
  { "word": "สถาบันหลัก", "count": 9, "summation": 1004328900 },
  { "word": "เงินอุดหนุนทั่วไป", "count": 313, "summation": 20378685850 },
  { "word": "อัธยาศัย", "count": 4, "summation": 67288500 }
]
